pyonepassword/__about__.py
pyonepassword/__init__.py
pyonepassword/_abc_meta.py
pyonepassword/_api_initializer.py
pyonepassword/_datetime.py
pyonepassword/_field_assignment.py
pyonepassword/_op_cli.py
pyonepassword/_op_cli_argv.py
pyonepassword/_op_cli_config.py
pyonepassword/_op_cli_version.py
pyonepassword/_op_commands.py
pyonepassword/_py_op_deprecation.py
pyonepassword/_svc_account.py
pyonepassword/account.py
pyonepassword/json.py
pyonepassword/logging.py
pyonepassword/op_objects.py
pyonepassword/opconfig_main.py
pyonepassword/opversion_main.py
pyonepassword/pkg_resources.py
pyonepassword/py.typed
pyonepassword/py_op_exceptions.py
pyonepassword/pyonepassword.py
pyonepassword/string.py
pyonepassword/version.py
pyonepassword/api/__init__.py
pyonepassword/api/authentication.py
pyonepassword/api/cli_version.py
pyonepassword/api/constants.py
pyonepassword/api/decorators.py
pyonepassword/api/descriptor_types.py
pyonepassword/api/exceptions.py
pyonepassword/api/object_types.py
pyonepassword/api/validation.py
pyonepassword/data/__init__.py
pyonepassword/data/api_credential.json
pyonepassword/data/bank_account.json
pyonepassword/data/credit_card.json
pyonepassword/data/crypto_wallet.json
pyonepassword/data/database.json
pyonepassword/data/document.json
pyonepassword/data/driver_license.json
pyonepassword/data/email_account.json
pyonepassword/data/identity.json
pyonepassword/data/login.json
pyonepassword/data/medical_record.json
pyonepassword/data/membership.json
pyonepassword/data/outdoor_license.json
pyonepassword/data/passport.json
pyonepassword/data/password.json
pyonepassword/data/reward_program.json
pyonepassword/data/secure_note.json
pyonepassword/data/server.json
pyonepassword/data/social_security_number.json
pyonepassword/data/software_license.json
pyonepassword/data/ssh_key.json
pyonepassword/data/template-registry.json
pyonepassword/data/wireless_router.json
pyonepassword/data/op_versions/__init__.py
pyonepassword/data/op_versions/version_support.json
pyonepassword-5.3.0.dist-info/licenses/LICENSE
pyonepassword-5.3.0.dist-info/METADATA
pyonepassword-5.3.0.dist-info/WHEEL
pyonepassword-5.3.0.dist-info/entry_points.txt
pyonepassword-5.3.0.dist-info/top_level.txt
pyonepassword-5.3.0.dist-info/RECORD
